Metadata-Version: 2.1
Name: iyaole
Version: 1.0.3
Summary: A light weight command line menu that supports Windows
Home-page: UNKNOWN
Author: mortal chen
Author-email: iyaole@vip.qq.com
License: UNKNOWN
Keywords: python,windows
Platform: UNKNOWN
Classifier: Development Status :: 1 - Planning
Classifier: Intended Audience :: Developers
Classifier: Programming Language :: Python :: 3
Classifier: Operating System :: Microsoft :: Windows
